{"stats":{"minecraft:picked_up":{"born_in_chaos_v1:charmof_stealth":1,"minecraft:wheat":38,"minecraft:anvil":4,"minecraft:smithing_table":1,"minecraft:brown_bed":5,"thalassophobia:tooth":18,"minecraft:brewing_stand":1,"farmersdelight:cutting_board":1,"minecraft:music_disc_cat":1,"minecraft:string":8,"minecraft:dark_oak_trapdoor":5,"minecraft:soul_soil":4,"minecraft:cooked_salmon":1,"minecraft:red_candle":6,"minecraft:shroomlight":7,"minecraft:beetroot":12,"alexsmobs:blood_sac":1,"minecraft:gold_nugget":37,"naturalist:cooked_catfish":2,"minecraft:spruce_planks":17,"crittersandcompanions:koi_fish":1,"born_in_chaos_v1:stimulating_decoction":1,"minecraft:melon_slice":25,"minecraft:smooth_quartz_stairs":1,"minecraft:furnace":3,"born_in_chaos_v1:soulbane":1,"minecraft:golden_helmet":1,"minecraft:stick":37,"minecraft:jukebox":1,"minecraft:deepslate_brick_wall":7,"minecraft:composter":3,"minecraft:birch_trapdoor":15,"minecraft:torch":11,"born_in_chaos_v1:pileof_dark_metal":1,"thalassophobia:sonar_organ":1,"minecraft:porkchop":6,"minecraft:cherry_log":69,"born_in_chaos_v1:nightmare_claw":2,"minecraft:cauldron":1,"minecraft:brown_carpet":2,"friendsandfoes:birch_beehive":1,"minecraft:cactus":5,"minecraft:rotten_flesh":44,"crittersandcompanions:dragonfly_wing":5,"minecraft:tropical_fish":2,"minecraft:iron_block":8,"minecraft:mangrove_roots":9,"minecraft:snowball":17,"alexsmobs:flying_fish":2,"minecraft:cobblestone":42,"upgrade_aquatic:driftwood_planks":4,"minecraft:pink_petals":297,"minecraft:feather":4,"minecraft:cherry_planks":17,"minecraft:birch_slab":5,"minecraft:smoker":2,"minecraft:potato":100,"create:raw_zinc":5,"minecraft:cherry_fence":1,"minecraft:stripped_birch_log":3,"minecraft:dirt":223,"minecraft:lantern":38,"born_in_chaos_v1:monster_skin":9,"minecraft:bone":26,"minecraft:stonecutter":1,"minecraft:wheat_seeds":119,"ribbits:maraca":3,"minecraft:grindstone":1,"minecraft:mossy_stone_bricks":8,"minecraft:fletching_table":1,"minecraft:bamboo":3,"alexsmobs:blobfish":2,"minecraft:oak_planks":12,"minecraft:honeycomb":9,"friendsandfoes:totem_of_freezing":4,"minecraft:sand":192,"minecraft:stripped_spruce_log":1,"chimes:iron_chimes":1,"minecraft:barrel":6,"minecraft:mossy_cobblestone":1,"upgrade_aquatic:lionfish":2,"upgrade_aquatic:perch":1,"some_assembly_required:sandwich":1,"born_in_chaos_v1:fire_dust":3,"minecraft:diamond":6,"minecraft:soul_lantern":7,"minecraft:blue_ice":3,"minecraft:white_concrete":7,"minecraft:emerald":81,"minecraft:bread":44,"minecraft:jack_o_lantern":1,"minecraft:netherrack":104,"minecraft:dark_oak_fence":13,"minecraft:oak_leaves":3,"minecraft:crimson_roots":9,"minecraft:ladder":162,"born_in_chaos_v1:seedof_chaos":5,"friendsandfoes:totem_of_illusion":1,"minecraft:quartz_slab":6,"minecraft:iron_axe":1,"create:scorchia":10,"born_in_chaos_v1:intoxicating_decoction":5,"minecraft:white_carpet":42,"minecraft:birch_fence":21,"minecraft:beef":7,"born_in_chaos_v1:gnawed_bones":1,"minecraft:player_head":1,"minecraft:chest":2,"minecraft:spruce_slab":6,"naturalist:catfish":1,"minecraft:sugar_cane":53,"minecraft:egg":8,"thalassophobia:raw_fish_meat":23,"minecraft:sandstone":26,"minecraft:raw_gold_block":3,"minecraft:spruce_fence":2,"born_in_chaos_v1:pieceofdarkmetal":25,"minecraft:carrot":143,"minecraft:dark_oak_planks":53,"minecraft:arrow":11,"minecraft:cooked_cod":2,"minecraft:beetroot_seeds":37,"born_in_chaos_v1:wood_splitter_axe":1,"upgrade_aquatic:driftwood_log":22,"minecraft:deepslate_bricks":2,"minecraft:diamond_boots":1,"minecraft:hay_block":7,"minecraft:black_banner":2,"thalassophobia:fish_scale":8,"born_in_chaos_v1:corpse_maggot":3,"minecraft:basalt":5,"minecraft:golden_carrot":5,"born_in_chaos_v1:monster_flesh":7,"minecraft:tripwire_hook":2,"minecraft:leather":6,"minecraft:birch_planks":154,"minecraft:oak_log":18,"minecraft:nether_wart_block":2,"minecraft:gunpowder":12,"minecraft:cobblestone_stairs":1,"another_furniture:cherry_chair":4,"alexsmobs:mosquito_proboscis":1,"minecraft:orange_terracotta":1,"minecraft:apple":1,"minecraft:stone_bricks":18,"thalassophobia:pearl":1,"minecraft:soul_sand":5,"minecraft:book":83,"minecraft:scaffolding":13,"upgrade_aquatic:driftwood_stairs":26,"born_in_chaos_v1:lifestealer_bone":4,"born_in_chaos_v1:ethereal_spirit":4,"minecraft:quartz":47,"minecraft:dandelion":1,"minecraft:birch_stairs":4,"minecraft:blast_furnace":2,"minecraft:spruce_log":47,"friendsandfoes:spruce_beehive":1,"naturalist:cooked_bass":1,"minecraft:diamond_shovel":2,"minecraft:slime_ball":4,"minecraft:painting":4,"minecraft:cherry_sapling":47,"born_in_chaos_v1:tombstone_dark_titan_066":2,"minecraft:mangrove_propagule":4,"minecraft:coal":52,"minecraft:ender_pearl":1},"minecraft:used":{"mcwfurnitures:oak_bookshelf":1,"minecraft:beetroot":6,"mcwfurnitures:oak_chair":2,"minecraft:cherry_sapling":1,"minecraft:polished_deepslate":2,"another_furniture:gray_sofa":4,"minecraft:light_gray_stained_glass_pane":50,"minecraft:dispenser":5,"minecraft:spruce_slab":63,"mcwdoors:oak_waffle_door":1,"minecraft:ladder":4,"farmersdelight:stove":6,"minecraft:chest":22,"minecraft:shield":42,"vinery:grapevine_leaves":6,"minecraft:iron_chestplate":1,"minecraft:white_candle":8,"minecraft:soul_sand":3,"another_furniture:brown_lamp":1,"mcwdoors:garage_white_door":2,"minecraft:carrot":16,"minecraft:deepslate_tile_slab":4,"another_furniture:cherry_chair":43,"minecraft:snowball":16,"minecraft:obsidian":18,"another_furniture:white_sofa":13,"born_in_chaos_v1:soulbane":332,"born_in_chaos_v1:smoked_flesh":3,"minecraft:quartz_slab":18,"minecraft:villager_spawn_egg":10,"minecraft:grass_block":14,"friendsandfoes:totem_of_illusion":1,"minecraft:lantern":151,"minecraft:polished_andesite_stairs":5,"mcwfurnitures:stripped_birch_modern_chair":2,"minecraft:item_frame":9,"minecraft:stone_bricks":376,"friendsandfoes:totem_of_freezing":2,"minecraft:birch_trapdoor":50,"farmersdelight:cutting_board":3,"ribbits:ribbit_merchant_spawn_egg":1,"minecraft:scaffolding":5,"minecraft:mangrove_roots":9,"minecraft:furnace":3,"minecraft:mangrove_slab":1,"minecraft:beetroot_seeds":24,"minecraft:egg":7,"minecraft:pearlescent_froglight":8,"minecraft:potato":25,"minecraft:mangrove_leaves":26,"farmersdelight:full_tatami_mat":7,"minecraft:deepslate_brick_wall":16,"minecraft:mossy_stone_bricks":8,"minecraft:spruce_door":2,"luphieclutteredmod:luphie_yellow_door":1,"minecraft:oak_planks":24,"minecraft:ender_pearl":2,"minecraft:sandstone":26,"minecraft:composter":2,"minecraft:sugar_cane":3,"minecraft:smooth_quartz_stairs":25,"minecraft:oak_leaves":94,"minecraft:glow_berries":6,"minecraft:golden_apple":2,"minecraft:sand":13,"minecraft:loom":1,"minecraft:ochre_froglight":9,"minecraft:blast_furnace":2,"luphieclutteredmod:luphie_brown_desk":1,"minecraft:stone_brick_wall":1,"some_assembly_required:sandwich":11,"upgrade_aquatic:tooth_lantern":1,"minecraft:birch_fence":101,"chimes:iron_chimes":2,"minecraft:birch_slab":21,"another_furniture:dark_oak_drawer":3,"minecraft:bread":59,"minecraft:lectern":1,"another_furniture:white_lamp":2,"upgrade_aquatic:tooth_trapdoor":9,"minecraft:iron_door":6,"minecraft:polished_andesite_slab":2,"upgrade_aquatic:lionfish":1,"born_in_chaos_v1:mesh_door":2,"minecraft:grindstone":3,"minecraft:smithing_table":1,"farmersdelight:spruce_cabinet":8,"minecraft:tropical_fish_bucket":5,"minecraft:white_concrete":548,"minecraft:bone_meal":240,"minecraft:oak_fence":7,"minecraft:oak_trapdoor":18,"luphieclutteredmod:luphie_darkwood_southern_flair_sofa":1,"minecraft:flint_and_steel":9,"born_in_chaos_v1:ethereal_spirit":3,"minecraft:light_gray_carpet":5,"farmersdelight:half_tatami_mat":10,"pizzadelight:pizza_station":1,"minecraft:spruce_planks":73,"luphieclutteredmod:pastel_yellow_flower_shelf_candle":2,"minecraft:netherrack":102,"minecraft:oak_door":4,"minecraft:torch":19,"minecraft:dirt":322,"minecraft:anvil":5,"minecraft:white_carpet":27,"ribbits:ribbit_gardener_spawn_egg":2,"upgrade_aquatic:driftwood_boat":3,"minecraft:spruce_stairs":200,"minecraft:spruce_fence":16,"minecraft:oak_fence_gate":7,"minecraft:shroomlight":7,"born_in_chaos_v1:supreme_measure":8,"minecraft:dark_oak_planks":5,"minecraft:bookshelf":4,"minecraft:light_gray_stained_glass":106,"endergetic:ender_lantern":2,"mcwfurnitures:oak_modern_chair":3,"upgrade_aquatic:lionfish_bucket":1,"minecraft:polished_deepslate_wall":1,"minecraft:iron_boots":2,"minecraft:barrel":13,"upgrade_aquatic:driftwood_door":1,"farmersdelight:canvas_rug":1,"upgrade_aquatic:tooth_door":1,"upgrade_aquatic:driftwood_stairs":74,"minecraft:tripwire_hook":3,"farmersdelight:basket":10,"mcwfences:iron_cheval_de_frise":1,"minecraft:golden_carrot":21,"minecraft:iron_trapdoor":4,"minecraft:deepslate_tile_stairs":5,"chimes:amethyst_chimes":3,"mcwdoors:oak_glass_door":1,"farmersdelight:cooking_pot":2,"some_assembly_required:sandwiching_station":2,"minecraft:cherry_fence":19,"minecraft:light_gray_bed":18,"minecraft:brown_bed":5,"minecraft:wheat_seeds":42,"minecraft:chiseled_bookshelf":4,"alexsmobs:cooked_catfish":1,"minecraft:water_bucket":90,"farmersdelight:skillet":2,"minecraft:cobblestone_stairs":3,"minecraft:birch_planks":48,"minecraft:polished_andesite":2,"minecraft:baked_potato":1,"ribbits:ribbit_sorcerer_spawn_egg":2,"minecraft:cartography_table":1,"ribbits:ribbit_nitwit_spawn_egg":4,"minecraft:cherry_planks":73,"luphieclutteredmod:luphie_pastry_display_case":4,"minecraft:spruce_sign":2,"minecraft:fletching_table":2,"minecraft:stonecutter":1,"minecraft:leather_boots":1,"minecraft:glow_item_frame":1,"upgrade_aquatic:driftwood_planks":13,"minecraft:mossy_cobblestone":1,"minecraft:music_disc_cat":1,"minecraft:vine":32,"another_furniture:oak_table":5,"minecraft:crafting_table":1,"minecraft:magenta_bed":1,"another_furniture:brown_tall_stool":1,"minecraft:campfire":4,"minecraft:cake":1,"mcwfurnitures:stripped_warped_desk":1,"minecraft:spruce_log":5,"minecraft:smoker":3,"luphieclutteredmod:luphie_darkwood_quilted_sofa":1,"minecraft:oak_log":8,"minecraft:flower_pot":10,"minecraft:diamond_pickaxe":180,"minecraft:diamond_shovel":1270,"minecraft:mangrove_propagule":6,"minecraft:oak_button":1,"mcwfurnitures:jungle_modern_chair":1,"minecraft:iron_pickaxe":274,"mcwwindows:one_way_glass":2,"minecraft:spruce_trapdoor":27,"ribbits:mossy_oak_door":2,"minecraft:pink_petals":10,"minecraft:cobblestone":22,"minecraft:purple_bed":1,"minecraft:white_banner":14,"born_in_chaos_v1:tombstone_dark_titan_066":1,"born_in_chaos_v1:wood_splitter_axe":713,"minecraft:bucket":49,"another_furniture:birch_table":25,"minecraft:pumpkin_pie":5,"mcwdoors:metal_hospital_door":1,"mcwdoors:dark_oak_bamboo_door":2,"minecraft:jukebox":1,"minecraft:birch_stairs":4},"minecraft:mined":{"minecraft:dark_oak_planks":1,"snowrealmagic:slab":1,"minecraft:spruce_planks":13,"vinery:dark_cherry_leaves":1,"minecraft:cobblestone_stairs":1,"minecraft:cherry_log":70,"minecraft:brewing_stand":1,"minecraft:grass_block":599,"minecraft:brown_wool":1,"minecraft:white_concrete":5,"minecraft:soul_soil":4,"minecraft:deepslate_bricks":2,"minecraft:composter":3,"minecraft:spawner":12,"friendsandfoes:spruce_beehive":1,"minecraft:dark_oak_trapdoor":5,"minecraft:fire":3,"minecraft:barrel":3,"minecraft:anvil":4,"minecraft:fletching_table":1,"minecraft:brown_bed":5,"minecraft:water_cauldron":1,"minecraft:cave_vines":4,"minecraft:iron_block":8,"minecraft:deepslate_brick_wall":7,"minecraft:smoker":2,"minecraft:crimson_nylium":3,"minecraft:orange_terracotta":1,"minecraft:soul_lantern":4,"minecraft:torch":4,"minecraft:blast_furnace":1,"minecraft:melon":1,"minecraft:chest":2,"minecraft:dead_bush":1,"born_in_chaos_v1:black_argillite_column_slab":1,"minecraft:glass":1,"minecraft:nether_quartz_ore":48,"minecraft:cobblestone":13,"chimes:iron_chimes":1,"minecraft:oak_planks":11,"minecraft:sugar_cane":13,"minecraft:grindstone":1,"minecraft:wall_torch":6,"minecraft:pink_petals":118,"minecraft:seagrass":8,"minecraft:cherry_fence":1,"minecraft:red_candle":3,"born_in_chaos_v1:tombstone_dark_titan_066":2,"minecraft:nether_wart_block":6,"minecraft:light_gray_stained_glass":8,"minecraft:wheat":38,"born_in_chaos_v1:fired_black_argillite":2,"minecraft:birch_trapdoor":14,"minecraft:jukebox":1,"minecraft:grass":68,"minecraft:oak_log":15,"minecraft:beetroots":12,"minecraft:dirt":473,"minecraft:sand":129,"vinery:apple_leaves":4,"minecraft:stonecutter":1,"minecraft:netherrack":101,"minecraft:oak_leaves":1,"create:zinc_ore":5,"minecraft:nether_gold_ore":6,"minecraft:mossy_cobblestone":2,"minecraft:dark_oak_leaves":7,"upgrade_aquatic:driftwood_stairs":26,"minecraft:stripped_birch_log":1,"minecraft:jack_o_lantern":1,"minecraft:mangrove_roots":9,"minecraft:ladder":162,"minecraft:dark_oak_fence":13,"minecraft:spruce_fence":2,"minecraft:crimson_roots":11,"minecraft:birch_slab":5,"minecraft:spruce_leaves":1,"minecraft:sandstone":26,"minecraft:mangrove_propagule":4,"minecraft:hay_block":7,"another_furniture:cherry_chair":4,"minecraft:furnace":3,"minecraft:carrots":22,"minecraft:raw_gold_block":3,"create:scorchia":10,"minecraft:stripped_spruce_log":1,"minecraft:bookshelf":28,"minecraft:potatoes":26,"minecraft:shroomlight":6,"minecraft:vine":2,"minecraft:lantern":15,"minecraft:stone":95,"upgrade_aquatic:driftwood_planks":4,"minecraft:smithing_table":1,"minecraft:birch_stairs":4,"minecraft:scaffolding":11,"minecraft:cherry_planks":19,"minecraft:soul_sand":5,"vinery:dark_cherry_log":6,"minecraft:brown_carpet":2,"minecraft:tall_grass":21,"friendsandfoes:birch_beehive":1,"minecraft:birch_planks":175,"minecraft:cactus":4,"minecraft:black_wall_banner":2,"minecraft:white_carpet":38,"minecraft:spruce_log":24,"minecraft:mangrove_leaves":1,"minecraft:coal_ore":16,"minecraft:cherry_leaves":4,"upgrade_aquatic:driftwood_log":22,"minecraft:stone_bricks":7,"minecraft:mossy_stone_bricks":8,"minecraft:birch_fence":20,"minecraft:fern":2},"minecraft:killed":{"born_in_chaos_v1:lifestealer_true_form":1,"born_in_chaos_v1:zombie_clown":1,"minecraft:spider":3,"born_in_chaos_v1:baby_skeleton_minion":4,"naturalist:snail":2,"minecraft:skeleton":4,"thalassophobia:colossoteus":1,"alexsmobs:straddler":1,"minecraft:illusioner":1,"minecraft:tropical_fish":2,"minecraft:piglin":7,"minecraft:parrot":1,"born_in_chaos_v1:bonescaller":1,"upgrade_aquatic:lionfish":1,"minecraft:zombie_villager":3,"born_in_chaos_v1:bone_imp":2,"alexsmobs:stradpole":1,"minecraft:creeper":1,"alexsmobs:crimson_mosquito":2,"minecraft:zombie":6,"born_in_chaos_v1:dread_hound":4,"ribbits:ribbit":7,"minecraft:stray":4,"minecraft:cow":4,"born_in_chaos_v1:missioner":1,"born_in_chaos_v1:zombie_clown_not_despawn":1,"minecraft:vindicator":23,"thalassophobia:megapiranha":1,"crittersandcompanions:dragonfly":5,"born_in_chaos_v1:zombie_bruiser":4,"born_in_chaos_v1:firelight":5,"born_in_chaos_v1:maggot":4,"alexsmobs:tusklin":1,"alexsmobs:flying_fish":2,"friendsandfoes:iceologer":3,"born_in_chaos_v1:fallen_chaos_knight":1,"born_in_chaos_v1:baby_skeleton":4,"born_in_chaos_v1:decrepit_skeleton":3,"born_in_chaos_v1:nightmare_stalker":1,"minecraft:villager":1,"born_in_chaos_v1:decaying_zombie_not_despawn":2,"minecraft:enderman":1},"minecraft:crafted":{"minecraft:oak_planks":16,"luphieclutteredmod:luphie_brown_desk":1,"minecraft:diamond_shovel":1,"minecraft:bow":1,"minecraft:oak_button":1,"minecraft:chest":7,"upgrade_aquatic:driftwood_boat":3,"minecraft:cod_bucket":1,"minecraft:arrow":128,"minecraft:emerald":22,"minecraft:crafting_table":1,"minecraft:diamond_axe":1,"minecraft:spruce_planks":40,"minecraft:baked_potato":3,"another_furniture:cherry_chair":3,"minecraft:diamond_pickaxe":1,"minecraft:stick":8,"minecraft:cherry_planks":80,"upgrade_aquatic:driftwood_planks":52,"minecraft:wheat":45,"minecraft:bucket":1,"minecraft:enchanted_book":2,"minecraft:air":0},"minecraft:custom":{"minecraft:animals_bred":32,"minecraft:interact_with_crafting_table":4,"minecraft:open_barrel":95,"minecraft:bell_ring":6,"minecraft:leave_game":9,"minecraft:time_since_death":119942,"minecraft:sprint_one_cm":1172160,"minecraft:damage_blocked_by_shield":1890,"minecraft:drop":377,"minecraft:play_noteblock":2,"minecraft:talked_to_villager":77,"minecraft:play_time":616497,"minecraft:deaths":29,"minecraft:jump":5497,"minecraft:interact_with_brewingstand":2,"minecraft:walk_on_water_one_cm":64823,"minecraft:interact_with_furnace":3,"minecraft:play_record":1,"minecraft:traded_with_villager":34,"minecraft:interact_with_cartography_table":1,"minecraft:interact_with_loom":1,"minecraft:sleep_in_bed":10,"some_assembly_required:burgers_eaten":5,"minecraft:damage_dealt":29517,"minecraft:crouch_one_cm":29751,"minecraft:interact_with_smoker":4,"minecraft:inspect_dispenser":3,"minecraft:interact_with_anvil":7,"minecraft:mob_kills":131,"minecraft:damage_dealt_resisted":528,"minecraft:climb_one_cm":15294,"minecraft:walk_one_cm":1499377,"minecraft:sneak_time":17642,"minecraft:walk_under_water_one_cm":103294,"minecraft:boat_one_cm":224219,"some_assembly_required:sandwiches_eaten":3,"minecraft:total_world_time":616497,"minecraft:tune_noteblock":9,"minecraft:interact_with_stonecutter":1,"minecraft:time_since_rest":119987,"minecraft:damage_taken":19238,"minecraft:damage_absorbed":48,"minecraft:trigger_trapped_chest":2,"minecraft:swim_one_cm":32451,"minecraft:fly_one_cm":3187997,"minecraft:open_chest":137,"minecraft:fall_one_cm":138376},"minecraft:killed_by":{"minecraft:wither_skeleton":1,"born_in_chaos_v1:zombie_bruiser":1,"alexsmobs:tusklin":1,"minecraft:vindicator":10,"minecraft:illusioner":3,"born_in_chaos_v1:lifestealer_true_form":1,"minecraft:player":1,"born_in_chaos_v1:restless_spirit":1,"born_in_chaos_v1:dark_vortex":1,"thalassophobia:colossoteus":2,"born_in_chaos_v1:missioner":2},"minecraft:broken":{"minecraft:golden_helmet":1,"minecraft:leather_leggings":1,"minecraft:iron_chestplate":1,"born_in_chaos_v1:wood_splitter_axe":1,"minecraft:leather_helmet":1,"minecraft:shield":1,"minecraft:leather_boots":1},"minecraft:dropped":{"minecraft:porkchop":14,"minecraft:diamond_axe":1,"minecraft:lantern":11,"minecraft:emerald":34,"upgrade_aquatic:driftwood_planks":1,"ribbits:maraca":3,"minecraft:dirt":6,"minecraft:birch_fence":1,"minecraft:dark_oak_fence":65,"minecraft:dark_oak_trapdoor":5,"minecraft:snowball":1,"minecraft:bone_meal":32,"minecraft:gold_nugget":8,"minecraft:sand":256,"minecraft:iron_pickaxe":1,"minecraft:dark_oak_planks":53,"minecraft:birch_log":128,"farmersdelight:mutton_chops":10,"minecraft:sugar_cane":19,"born_in_chaos_v1:ethereal_spirit":1,"minecraft:rotten_flesh":35,"minecraft:diamond_shovel":2,"minecraft:carrot":123,"sophisticatedbackpacks:diamond_backpack":1,"sophisticatedbackpacks:smoking_upgrade":1,"minecraft:leather_chestplate":1,"alexsmobs:blood_sac":1,"minecraft:birch_trapdoor":1,"minecraft:stone_brick_wall":1,"minecraft:ladder":1,"minecraft:chest":1,"minecraft:beef":9,"minecraft:quartz":47,"minecraft:oak_leaves":3,"mcwdoors:oak_barn_glass_door":1,"minecraft:netherrack":1,"alexsmobs:mosquito_proboscis":1,"minecraft:enchanted_book":1,"minecraft:bread":43,"born_in_chaos_v1:intoxicating_decoction":2,"born_in_chaos_v1:wood_splitter_axe":2,"minecraft:wheat_seeds":14,"minecraft:book":16,"minecraft:cobblestone":2,"minecraft:coal":98,"minecraft:stick":4,"born_in_chaos_v1:soulbane":2,"minecraft:golden_carrot":69,"minecraft:white_concrete":99,"minecraft:cherry_planks":2,"minecraft:light_gray_stained_glass":45,"minecraft:stripped_birch_log":2,"farmersdelight:bacon":5,"minecraft:iron_axe":1,"sophisticatedbackpacks:crafting_upgrade":1,"minecraft:paper":33,"minecraft:pink_petals":152,"minecraft:music_disc_cat":1,"minecraft:spruce_sapling":1,"create:andesite_door":1,"minecraft:sweet_berries":30,"friendsandfoes:totem_of_freezing":2,"naturalist:cooked_catfish":1,"minecraft:player_head":1,"alexsmobs:blobfish":2,"minecraft:iron_boots":1,"minecraft:spruce_fence":1,"minecraft:blast_furnace":1,"minecraft:shroomlight":1,"minecraft:shield":1,"minecraft:orange_terracotta":1,"minecraft:spruce_planks":2,"minecraft:mossy_stone_bricks":16,"farmersdelight:minced_beef":5,"minecraft:stone_bricks":25,"minecraft:barrel":3,"minecraft:spruce_log":48,"born_in_chaos_v1:chocolate_heart":2,"luphieclutteredmod:luphie_brown_desk":1}},"DataVersion":3465}